wwu_tinker/__init__.py
wwu_tinker/configuration.py
wwu_tinker/experiment.py
wwu_tinker/variable.py
wwu_tinker-0.1a2.dist-info/METADATA
wwu_tinker-0.1a2.dist-info/RECORD
wwu_tinker-0.1a2.dist-info/WHEEL
wwu_tinker-0.1a2.dist-info/top_level.txt
